xlstotex/__init__.py
xlstotex/cmd.py
xlstotex/convert.py
xlstotex/utils.py
xlstotex-0.0.1.dist-info/LICENSE
xlstotex-0.0.1.dist-info/METADATA
xlstotex-0.0.1.dist-info/WHEEL
xlstotex-0.0.1.dist-info/entry_points.txt
xlstotex-0.0.1.dist-info/top_level.txt
xlstotex-0.0.1.dist-info/RECORD
